{"grouped_by":null,"sub_grouped_by":null,"total_count":10,"next_cursor":"1000:1:0","prev_cursor":"1000:-1:1","next_page_results":false,"prev_page_results":false,"count":10,"total_pages":1,"total_results":10,"extra_stats":null,"results":[{"id":"dff694be-63b4-40bc-ade8-96920df9673d","created_at":"2026-06-30T21:56:48.678909+03:00","updated_at":"2026-06-30T21:56:48.678931+03:00","deleted_at":null,"name":"growth-task","description":"","color":"#f78da7","sort_order":155535.0,"external_source":null,"external_id":null,"created_by":"e12805b3-4184-468c-bb7f-a8a11b5efdf6","updated_by":null,"workspace":"c81d4a58-ee30-4b3f-9221-cc1d95566440","project":"e608e7ad-f4fe-401d-b0f3-5570e82f08ee","parent":null},{"id":"caa1adb5-1451-48dd-9d07-8e1c641c633e","created_at":"2026-06-30T21:56:34.261606+03:00","updated_at":"2026-06-30T21:56:34.261628+03:00","deleted_at":null,"name":"urgent","description":"","color":"#ff6900","sort_order":145535.0,"external_source":null,"external_id":null,"created_by":"e12805b3-4184-468c-bb7f-a8a11b5efdf6","updated_by":null,"workspace":"c81d4a58-ee30-4b3f-9221-cc1d95566440","project":"e608e7ad-f4fe-401d-b0f3-5570e82f08ee","parent":null},{"id":"97ee2eee-eaa8-4fd6-8742-dd9c46e54979","created_at":"2026-06-30T21:56:23.986204+03:00","updated_at":"2026-06-30T21:56:23.986223+03:00","deleted_at":null,"name":"refactoring","description":"","color":"#fcb900","sort_order":135535.0,"external_source":null,"external_id":null,"created_by":"e12805b3-4184-468c-bb7f-a8a11b5efdf6","updated_by":null,"workspace":"c81d4a58-ee30-4b3f-9221-cc1d95566440","project":"e608e7ad-f4fe-401d-b0f3-5570e82f08ee","parent":null},{"id":"5b1f0192-7664-4679-b2c3-98e1fe8a4e8e","created_at":"2026-06-30T21:56:15.549317+03:00","updated_at":"2026-06-30T21:56:15.549341+03:00","deleted_at":null,"name":"feature","description":"","color":"#8ed1fc","sort_order":125535.0,"external_source":null,"external_id":null,"created_by":"e12805b3-4184-468c-bb7f-a8a11b5efdf6","updated_by":null,"workspace":"c81d4a58-ee30-4b3f-9221-cc1d95566440","project":"e608e7ad-f4fe-401d-b0f3-5570e82f08ee","parent":null},{"id":"ce9f294a-bef7-4441-97b3-49576aafc371","created_at":"2026-06-30T21:56:07.237867+03:00","updated_at":"2026-06-30T21:56:07.237892+03:00","deleted_at":null,"name":"bug","description":"","color":"#eb144c","sort_order":115535.0,"external_source":null,"external_id":null,"created_by":"e12805b3-4184-468c-bb7f-a8a11b5efdf6","updated_by":null,"workspace":"c81d4a58-ee30-4b3f-9221-cc1d95566440","project":"e608e7ad-f4fe-401d-b0f3-5570e82f08ee","parent":null},{"id":"a12c8e8c-3bf5-49c7-a20a-43a344e07090","created_at":"2026-06-30T21:55:59.237948+03:00","updated_at":"2026-06-30T21:55:59.237969+03:00","deleted_at":null,"name":"devops","description":"","color":"#abb8c3","sort_order":105535.0,"external_source":null,"external_id":null,"created_by":"e12805b3-4184-468c-bb7f-a8a11b5efdf6","updated_by":null,"workspace":"c81d4a58-ee30-4b3f-9221-cc1d95566440","project":"e608e7ad-f4fe-401d-b0f3-5570e82f08ee","parent":null},{"id":"bb5f64d5-870a-4b26-bbd4-980b983c7261","created_at":"2026-06-30T21:55:41.917028+03:00","updated_at":"2026-06-30T21:55:41.917053+03:00","deleted_at":null,"name":"data","description":"","color":"#7bdcb5","sort_order":95535.0,"external_source":null,"external_id":null,"created_by":"e12805b3-4184-468c-bb7f-a8a11b5efdf6","updated_by":null,"workspace":"c81d4a58-ee30-4b3f-9221-cc1d95566440","project":"e608e7ad-f4fe-401d-b0f3-5570e82f08ee","parent":null},{"id":"754b3ad4-c8ce-4f8a-8c93-4013e6e6acd0","created_at":"2026-06-30T21:55:29.588863+03:00","updated_at":"2026-06-30T21:55:29.588885+03:00","deleted_at":null,"name":"ml","description":"","color":"#00d084","sort_order":85535.0,"external_source":null,"external_id":null,"created_by":"e12805b3-4184-468c-bb7f-a8a11b5efdf6","updated_by":null,"workspace":"c81d4a58-ee30-4b3f-9221-cc1d95566440","project":"e608e7ad-f4fe-401d-b0f3-5570e82f08ee","parent":null},{"id":"8d02ccac-3438-492c-b087-f54c12abb6fd","created_at":"2026-06-30T21:55:18.209951+03:00","updated_at":"2026-06-30T21:55:18.209969+03:00","deleted_at":null,"name":"frontend","description":"","color":"#9900ef","sort_order":75535.0,"external_source":null,"external_id":null,"created_by":"e12805b3-4184-468c-bb7f-a8a11b5efdf6","updated_by":null,"workspace":"c81d4a58-ee30-4b3f-9221-cc1d95566440","project":"e608e7ad-f4fe-401d-b0f3-5570e82f08ee","parent":null},{"id":"19ad9f4d-9f1f-4518-9076-419b4fb2f3e5","created_at":"2026-06-30T21:55:06.066284+03:00","updated_at":"2026-06-30T21:55:06.066314+03:00","deleted_at":null,"name":"backend","description":"","color":"#0693e3","sort_order":65535.0,"external_source":null,"external_id":null,"created_by":"e12805b3-4184-468c-bb7f-a8a11b5efdf6","updated_by":null,"workspace":"c81d4a58-ee30-4b3f-9221-cc1d95566440","project":"e608e7ad-f4fe-401d-b0f3-5570e82f08ee","parent":null}]}